docsub/__base__.py
docsub/__init__.py
docsub/__main__.py
docsub/config.py
docsub/environment.py
docsub/logging.py
docsub/process.py
docsub/py.typed
docsub/commands/__init__.py
docsub/commands/exec.py
docsub/commands/help.py
docsub/commands/include.py
docsub/commands/lines.py
docsub/commands/strip.py
docsub/commands/x.py
docsub/processors/md.py
docsub-0.8.3.dist-info/METADATA
docsub-0.8.3.dist-info/WHEEL
docsub-0.8.3.dist-info/entry_points.txt
docsub-0.8.3.dist-info/licenses/LICENSE
docsub-0.8.3.dist-info/RECORD
