Metadata-Version: 2.4
Name: docsub
Version: 0.8.3
Summary: Embed text and data into Markdown files
Project-URL: Homepage, https://github.com/makukha/docsub
Project-URL: Repository, https://github.com/makukha/docsub
Project-URL: Issues, https://github.com/makukha/docsub/issues
Project-URL: Changelog, https://github.com/makukha/docsub/releases
License: MIT
License-File: LICENSE
Keywords: docs,documentation,python,template-engine
Classifier: Development Status :: 4 - Beta
Classifier: Environment :: Console
Classifier: Intended Audience :: Developers
Classifier: Intended Audience :: Education
Classifier: Intended Audience :: Science/Research
Classifier: Intended Audience :: System Administrators
Classifier: License :: OSI Approved :: MIT License
Classifier: Operating System :: OS Independent
Classifier: Programming Language :: Python
Classifier: Programming Language :: Python :: 3
Classifier: Programming Language :: Python :: 3.9
Classifier: Programming Language :: Python :: 3.10
Classifier: Programming Language :: Python :: 3.11
Classifier: Programming Language :: Python :: 3.12
Classifier: Programming Language :: Python :: 3.13
Classifier: Programming Language :: Python :: 3.14
Classifier: Programming Language :: Python :: Implementation :: CPython
Classifier: Topic :: Documentation
Classifier: Topic :: Software Development
Classifier: Topic :: Software Development :: Documentation
Classifier: Topic :: Software Development :: Libraries
Classifier: Topic :: Text Processing :: Markup
Classifier: Topic :: Utilities
Classifier: Typing :: Typed
Requires-Python: >=3.9
Requires-Dist: importloc<0.4,>=0.3
Requires-Dist: loguru>=0.7
Requires-Dist: pydantic-settings>=2.7
Requires-Dist: rich-click>=1.8
Requires-Dist: typing-extensions>=4.5
